django5_aliyun_oss/__init__.py
django5_aliyun_oss/apps.py
django5_aliyun_oss/storage.py
django5_aliyun_oss/tests/__init__.py
django5_aliyun_oss/tests/test_storage.py
django5_aliyun_oss-1.1.2.dist-info/LICENSE
django5_aliyun_oss-1.1.2.dist-info/METADATA
django5_aliyun_oss-1.1.2.dist-info/WHEEL
django5_aliyun_oss-1.1.2.dist-info/top_level.txt
django5_aliyun_oss-1.1.2.dist-info/RECORD
