Metadata-Version: 2.1
Name: django5-aliyun-oss
Version: 1.1.2
Summary: Django5 storage backend for Aliyun OSS
Home-page: https://github.com/mircool/django-aliyun-oss
Author: Mircool
Project-URL: Bug Tracker, https://github.com/mircool/django-aliyun-oss/issues
Keywords: django,aliyun,oss,storage,file upload
Classifier: Development Status :: 5 - Production/Stable
Classifier: Environment :: Web Environment
Classifier: Framework :: Django
Classifier: Framework :: Django :: 5.0
Classifier: Intended Audience :: Developers
Classifier: License :: OSI Approved :: MIT License
Classifier: Operating System :: OS Independent
Classifier: Programming Language :: Python :: 3
Classifier: Programming Language :: Python :: 3.8
Classifier: Programming Language :: Python :: 3.9
Classifier: Programming Language :: Python :: 3.10
Classifier: Programming Language :: Python :: 3.11
Classifier: Programming Language :: Python :: 3.12
Classifier: Topic :: Internet :: WWW/HTTP
Requires-Python: >=3.8
License-File: LICENSE
Requires-Dist: Django>=5.0
Requires-Dist: oss2>=2.15.0
